gbml/__init__.py
gbml/core.cpython-36m-darwin.so
gbml/elasticity.py
gbml/data/element_aiab_energy.json
gbml/data/gbml-G-v1.00.data
gbml/data/gbml-K-v1.00.data
gbml-1.1.0.dist-info/METADATA
gbml-1.1.0.dist-info/RECORD
gbml-1.1.0.dist-info/WHEEL
gbml-1.1.0.dist-info/top_level.txt
