Metadata-Version: 2.1
Name: gbml
Version: 1.1.0
Summary: GBM-Locfit: A GBM framework using Locfit
Home-page: https://github.com/materialsproject/gbml/
Author: Randy Notestine
Author-email: RNotestine@UCSD.edu
License: GPL2
Platform: UNKNOWN
Classifier: Programming Language :: Python :: 3
Requires-Python: >=3
Requires-Dist: numpy
Requires-Dist: pymatgen
